phantom_guard/__init__.py
phantom_guard/py.typed
phantom_guard/cache/__init__.py
phantom_guard/cache/cache.py
phantom_guard/cache/memory.py
phantom_guard/cache/sqlite.py
phantom_guard/cache/types.py
phantom_guard/cli/__init__.py
phantom_guard/cli/branding.py
phantom_guard/cli/formatters.py
phantom_guard/cli/main.py
phantom_guard/cli/output.py
phantom_guard/cli/parsers.py
phantom_guard/cli/theme.py
phantom_guard/core/__init__.py
phantom_guard/core/batch.py
phantom_guard/core/detector.py
phantom_guard/core/patterns.py
phantom_guard/core/scorer.py
phantom_guard/core/types.py
phantom_guard/core/typosquat.py
phantom_guard/core/signals/__init__.py
phantom_guard/core/signals/combination.py
phantom_guard/core/signals/downloads.py
phantom_guard/core/signals/legacy.py
phantom_guard/core/signals/namespace.py
phantom_guard/core/signals/ownership.py
phantom_guard/core/signals/versions.py
phantom_guard/data/__init__.py
phantom_guard/data/popular_packages.py
phantom_guard/patterns/__init__.py
phantom_guard/patterns/community.py
phantom_guard/patterns/validate.py
phantom_guard/registry/__init__.py
phantom_guard/registry/cached.py
phantom_guard/registry/crates.py
phantom_guard/registry/exceptions.py
phantom_guard/registry/npm.py
phantom_guard/registry/pypi.py
phantom_guard/registry/retry.py
phantom_guard-0.2.0.dist-info/METADATA
phantom_guard-0.2.0.dist-info/WHEEL
phantom_guard-0.2.0.dist-info/entry_points.txt
phantom_guard-0.2.0.dist-info/licenses/LICENSE
phantom_guard-0.2.0.dist-info/RECORD
