Metadata-Version: 2.4
Name: phantom-guard
Version: 0.2.0
Summary: Detect AI-hallucinated package attacks (slopsquatting)
Project-URL: Homepage, https://github.com/phantom-guard/phantom-guard
Project-URL: Documentation, https://github.com/phantom-guard/phantom-guard#readme
Project-URL: Repository, https://github.com/phantom-guard/phantom-guard
Project-URL: Changelog, https://github.com/phantom-guard/phantom-guard/blob/main/CHANGELOG.md
Project-URL: Bug Tracker, https://github.com/phantom-guard/phantom-guard/issues
Author-email: Matteo Panzeri <matteo1782@gmail.com>
License: MIT License
License-File: LICENSE
Keywords: ai-security,package-validation,security,slopsquatting,supply-chain
Classifier: Development Status :: 3 - Alpha
Classifier: Intended Audience :: Developers
Classifier: License :: OSI Approved :: MIT License
Classifier: Programming Language :: Python :: 3.11
Classifier: Programming Language :: Python :: 3.12
Classifier: Topic :: Security
Classifier: Topic :: Software Development :: Libraries :: Python Modules
Classifier: Typing :: Typed
Requires-Python: >=3.11
Requires-Dist: aiosqlite>=0.19.0
Requires-Dist: httpx>=0.25.0
Requires-Dist: platformdirs>=4.0.0
Requires-Dist: pydantic>=2.5.0
Requires-Dist: pyyaml>=6.0.0
Requires-Dist: rich>=13.0.0
Requires-Dist: typer>=0.9.0
Provides-Extra: dev
Requires-Dist: hypothesis>=6.92.0; extra == 'dev'
Requires-Dist: memory-profiler>=0.61.0; extra == 'dev'
Requires-Dist: mypy>=1.8.0; extra == 'dev'
Requires-Dist: pytest-asyncio>=0.21.0; extra == 'dev'
Requires-Dist: pytest-benchmark>=4.0.0; extra == 'dev'
Requires-Dist: pytest-cov>=4.1.0; extra == 'dev'
Requires-Dist: pytest>=7.4.0; extra == 'dev'
Requires-Dist: respx>=0.20.0; extra == 'dev'
Requires-Dist: ruff>=0.1.0; extra == 'dev'
Requires-Dist: types-pyyaml>=6.0.0; extra == 'dev'
